antarys/__init__.py
antarys/_client.py
antarys/_embed_ops.py
antarys/_types.py
antarys/_vector_ops.py
antarys/py.typed
antarys-0.2.0.dist-info/licenses/LICENSE
antarys-0.2.0.dist-info/METADATA
antarys-0.2.0.dist-info/WHEEL
antarys-0.2.0.dist-info/top_level.txt
antarys-0.2.0.dist-info/RECORD
