Metadata-Version: 2.4
Name: antarys
Version: 0.2.0
Summary: High-performance Python client for Antarys vector database
Home-page: https://github.com/antarys-ai/antarys-python/
Author: Antarys
Author-email: antarys.ai@gmail.com
Classifier: Development Status :: 4 - Beta
Classifier: Intended Audience :: Developers
Classifier: License :: OSI Approved :: MIT License
Classifier: Programming Language :: Python :: 3
Classifier: Programming Language :: Python :: 3.8
Classifier: Programming Language :: Python :: 3.9
Classifier: Programming Language :: Python :: 3.10
Classifier: Programming Language :: Python :: 3.11
Classifier: Programming Language :: Python :: 3.12
Classifier: Programming Language :: Python :: 3.13
Classifier: Topic :: Scientific/Engineering :: Artificial Intelligence
Classifier: Topic :: Database :: Database Engines/Servers
Requires-Python: >=3.8
License-File: LICENSE
Requires-Dist: httpx>=0.25.0
Requires-Dist: numpy>=1.24.0
Requires-Dist: orjson>=3.9.0
Requires-Dist: tqdm>=4.65.0
Requires-Dist: cachetools>=5.3.0
Provides-Extra: all
Requires-Dist: numba>=0.58.0; extra == "all"
Requires-Dist: lz4>=4.3.2; extra == "all"
Requires-Dist: ujson>=5.8.0; extra == "all"
Provides-Extra: acceleration
Requires-Dist: numba>=0.58.0; extra == "acceleration"
Dynamic: author
Dynamic: author-email
Dynamic: classifier
Dynamic: description
Dynamic: description-content-type
Dynamic: home-page
Dynamic: license-file
Dynamic: provides-extra
Dynamic: requires-dist
Dynamic: requires-python
Dynamic: summary
